[
  {
    "id": "horse-run",
    "name": "Koşan At",
    "imageName": "horse",
    "imageUrl": "https://raw.githubusercontent.com/AbdlkdrTpc/phenakistoscope-discs/main/images/horse.png",
    "frameCount": 12,
    "description": "Muybridge'in ünlü koşan at animasyonu",
    "icon": "figure.equestrian.sports",
    "colorHex": "#FF6B6B",
    "addedDate": "2025-10-10T10:00:00Z",
    "recommendedSpeed": 2.5,
    "clockwise": true,
    "story": [
      "1878 yılında Eadweard Muybridge,",
      "atın koşarken dört ayağını birden",
      "yerden kesip kesmediğini kanıtlamak için",
      "bu tarihi fotoğraf serisini çekti.",
      "Sonuç: Evet, kesiyordu!"
    ]
  },
  {
    "id": "dancer-ballet",
    "name": "Bale Dansçısı",
    "imageName": "dancer",
    "imageUrl": "https://raw.githubusercontent.com/AbdlkdrTpc/phenakistoscope-discs/main/images/dancer.png",
    "frameCount": 10,
    "description": "Zarif dönüş hareketi",
    "icon": "figure.dance",
    "colorHex": "#9B59B6",
    "addedDate": "2025-10-10T14:00:00Z",
    "recommendedSpeed": 3.0,
    "clockwise": false,
    "story": [
      "Klasik bale hareketlerinden",
      "pirouette'in sihirli dönüşü,",
      "10 karede yakalanmış.",
      "Her hareket, mükemmel bir denge."
    ]
  },
  {
    "id": "bird-flight",
    "name": "Uçan Kuş",
    "imageName": "bird",
    "imageUrl": "https://raw.githubusercontent.com/AbdlkdrTpc/phenakistoscope-discs/main/images/bird.png",
    "frameCount": 8,
    "description": "Kanat çırpışının anatomisi",
    "icon": "bird.fill",
    "colorHex": "#3498DB",
    "addedDate": "2025-10-10T09:00:00Z",
    "recommendedSpeed": 2.0,
    "clockwise": true,
    "story": [
      "Leonardo da Vinci'nin kuş uçuşu",
      "çalışmalarından ilham alınmış.",
      "Kanatların aerodinamik hareketi",
      "frame by frame."
    ]
  }
]
